snakeribbon/__init__.py
snakeribbon/category.py
snakeribbon/constants.py
snakeribbon/gallery.py
snakeribbon/logger.py
snakeribbon/menu.py
snakeribbon/panel.py
snakeribbon/ribbonbar.py
snakeribbon/separator.py
snakeribbon/tabbar.py
snakeribbon/titlewidget.py
snakeribbon/toolbutton.py
snakeribbon/utils.py
snakeribbon-1.0.3.dev0.dist-info/LICENSE
snakeribbon-1.0.3.dev0.dist-info/METADATA
snakeribbon-1.0.3.dev0.dist-info/WHEEL
snakeribbon-1.0.3.dev0.dist-info/top_level.txt
snakeribbon-1.0.3.dev0.dist-info/RECORD
