Metadata-Version: 2.1
Name: snakeribbon
Version: 1.0.3.dev0
Summary: Ribbon Bar for PySide6 applications
Author-email: WANG Hailin <hailin.wang@connect.polyu.hk>, Ivanov Cyril <woah.npc@yandex.ru>
Project-URL: GitHub, https://github.com/uselessvevo/snakeribbon
Classifier: Programming Language :: Python
Classifier: Programming Language :: Python :: 3
Classifier: Programming Language :: Python :: 3.8
Classifier: Programming Language :: Python :: 3.9
Classifier: Programming Language :: Python :: 3.10
Classifier: Programming Language :: Python :: 3.11
Classifier: Programming Language :: Python :: 3.12
Classifier: Programming Language :: Python :: 3.13
Classifier: License :: OSI Approved :: MIT License
Classifier: Operating System :: OS Independent
Classifier: Development Status :: 4 - Beta
Requires-Python: >=3.8
License-File: LICENSE
